README.rst
setup.py
getl/__init__.py
getl.egg-info/PKG-INFO
getl.egg-info/SOURCES.txt
getl.egg-info/dependency_links.txt
getl.egg-info/top_level.txt
getl/extractors/__init__.py
getl/extractors/extractor.py
getl/extractors/location_history.py
tests/__init__.py
tests/test.py