Metadata-Version: 1.2
Name: getl
Version: 0.2
Summary: UNKNOWN
Home-page: https://github.com/gregology/getl
Author: Greg Clarke
Author-email: greg@gho.st
License: MIT
Keywords: google,takeout,data
Platform: UNKNOWN
Classifier: Development Status :: 4 - Beta
Classifier: Intended Audience :: Developers
Classifier: Topic :: Software Development :: Build Tools
Classifier: License :: OSI Approved :: MIT License
Classifier: Programming Language :: Python
Requires-Python: >=3
